separable_operator_networks/__init__.py
separable_operator_networks/eval.py
separable_operator_networks/hvp.py
separable_operator_networks/models.py
separable_operator_networks/train.py
separable_operator_networks/utils.py
separable_operator_networks/pde/__init__.py
separable_operator_networks/pde/advection.py
separable_operator_networks/pde/burgers.py
separable_operator_networks/pde/diffusion_reaction.py
separable_operator_networks/pde/heat.py
separable_operator_networks/pde/nonlinear_diffusion.py
separable_operator_networks-0.0.2.dist-info/METADATA
separable_operator_networks-0.0.2.dist-info/WHEEL
separable_operator_networks-0.0.2.dist-info/licenses/LICENSE.md
separable_operator_networks-0.0.2.dist-info/RECORD
