Metadata-Version: 2.3
Name: separable-operator-networks
Version: 0.0.2
Summary: Separable operator models for extreme-scale learning of parametric PDEs
Project-URL: Homepage, https://github.com/hewlettpackard/separable-operator-networks
Project-URL: Issues, https://github.com/hewlettpackard/separable-operator-networks/issues
Project-URL: Repository, https://github.com/hewlettpackard/separable-operator-networks.git
Author-email: Sean Hooten <sean.hooten@hpe.com>, Xinling Yu <xyu644@ucsb.edu>
Maintainer-email: Sean Hooten <sean.hooten@hpe.com>, Xinling Yu <xyu644@ucsb.edu>
License: Copyright (c) 2024 Hewlett Packard Development Enterprise LP
License-File: LICENSE.md
Keywords: DeepONet,PDE,deep operator network,operator learning,partial differential equations,phyics-informed neural network,scientific machine learning
Classifier: Development Status :: 3 - Alpha
Classifier: Intended Audience :: Science/Research
Classifier: License :: OSI Approved :: MIT License
Classifier: Operating System :: OS Independent
Classifier: Programming Language :: Python :: 3.8
Classifier: Programming Language :: Python :: 3.9
Classifier: Programming Language :: Python :: 3.10
Classifier: Programming Language :: Python :: 3.11
Classifier: Programming Language :: Python :: 3.12
Classifier: Topic :: Scientific/Engineering :: Artificial Intelligence
Classifier: Topic :: Scientific/Engineering :: Physics
Requires-Python: >=3.8
Requires-Dist: diffrax
Requires-Dist: equinox
Requires-Dist: gputil
Requires-Dist: jax
Requires-Dist: numpy
Requires-Dist: optax
Requires-Dist: scipy
Provides-Extra: cuda12
Requires-Dist: jax[cuda12]; extra == 'cuda12'
